uips/__init__.py
uips/sampler.py
uips/version.py
uips/wrapper.py
uips/cutils/__init__.py
uips/cutils/io.py
uips/cutils/misc.py
uips/inputs/input2D
uips/inputs/input2D_bins
uips/nde/__init__.py
uips/nde/distributions/__init__.py
uips/nde/distributions/base.py
uips/nde/distributions/discrete.py
uips/nde/distributions/discrete_test.py
uips/nde/distributions/mixture.py
uips/nde/distributions/normal.py
uips/nde/distributions/normal_test.py
uips/nde/distributions/uniform.py
uips/nde/flows/__init__.py
uips/nde/flows/autoregressive.py
uips/nde/flows/autoregressive_test.py
uips/nde/flows/base.py
uips/nde/flows/base_test.py
uips/nde/flows/realnvp.py
uips/nde/flows/realnvp_test.py
uips/nde/transforms/__init__.py
uips/nde/transforms/autoregressive.py
uips/nde/transforms/autoregressive_test.py
uips/nde/transforms/base.py
uips/nde/transforms/base_test.py
uips/nde/transforms/conv.py
uips/nde/transforms/conv_test.py
uips/nde/transforms/coupling.py
uips/nde/transforms/coupling_test.py
uips/nde/transforms/linear.py
uips/nde/transforms/linear_test.py
uips/nde/transforms/lu.py
uips/nde/transforms/lu_test.py
uips/nde/transforms/made.py
uips/nde/transforms/made_test.py
uips/nde/transforms/nonlinearities.py
uips/nde/transforms/nonlinearities_test.py
uips/nde/transforms/normalization.py
uips/nde/transforms/normalization_test.py
uips/nde/transforms/orthogonal.py
uips/nde/transforms/orthogonal_test.py
uips/nde/transforms/permutations.py
uips/nde/transforms/permutations_test.py
uips/nde/transforms/qr.py
uips/nde/transforms/qr_test.py
uips/nde/transforms/reshape.py
uips/nde/transforms/reshape_test.py
uips/nde/transforms/standard.py
uips/nde/transforms/standard_test.py
uips/nde/transforms/svd.py
uips/nde/transforms/svd_test.py
uips/nde/transforms/transform_test.py
uips/nde/transforms/splines/__init__.py
uips/nde/transforms/splines/cubic.py
uips/nde/transforms/splines/cubic_test.py
uips/nde/transforms/splines/linear.py
uips/nde/transforms/splines/linear_test.py
uips-0.1.0.dist-info/LICENSE
uips-0.1.0.dist-info/METADATA
uips-0.1.0.dist-info/WHEEL
uips-0.1.0.dist-info/top_level.txt
uips-0.1.0.dist-info/RECORD
