Metadata-Version: 2.1
Name: uips
Version: 0.1.0
Summary: Reduce a large and high-dimensional dataset by downselecting data uniformly in phase space
Home-page: https://github.com/NREL/Phase-space-sampling
Author: Malik Hassanaly
License: BSD 3-Clause
Classifier: Intended Audience :: Science/Research
Classifier: License :: OSI Approved :: BSD License
Classifier: Natural Language :: English
Classifier: Programming Language :: Python :: 3.10
Requires-Python: >=3.10
License-File: LICENSE
Requires-Dist: torch
Requires-Dist: numpy
Requires-Dist: mpi4py
Requires-Dist: scikit-learn
Requires-Dist: prettyPlot >=0.0.25
